[{"BACKGROUND":["ZIR:bidRangeMin_0_bidRangeMax_7500","ZIR:bidRangeMin_1000_bidRangeMax_2000"],"MARKETMAKER":["NOOP"]},{"BACKGROUND":["ZIR:bidRangeMin_5000_bidRangeMax_10000"],"MARKETMAKER":["NOOP"]},{"BACKGROUND":["ZIR:bidRangeMin_0_bidRangeMax_2000","ZIR:bidRangeMin_100000_bidRangeMax_125000"],"MARKETMAKER":["NOOP"]},{"BACKGROUND":["ZIR:bidRangeMin_0_bidRangeMax_1000","ZIR:bidRangeMin_100000_bidRangeMax_125000"],"MARKETMAKER":["NOOP"]},{"BACKGROUND":["NOOP","ZIR:bidRangeMin_100000_bidRangeMax_125000"],"MARKETMAKER":["NOOP"]},{"BACKGROUND":["NOOP","ZIR:bidRangeMin_0_bidRangeMax_1000","ZIR:bidRangeMin_0_bidRangeMax_2500"],"MARKETMAKER":["NOOP"]},{"BACKGROUND":["ZIP:marginMin_0.05_marginMax_0.35_gammaMin_0.1_gammaMax_0.1_betaMin_0.5_betaMax_0.5_rangeA_0.05_rangeR_0.05","ZIR:bidRangeMin_0_bidRangeMax_1000"],"MARKETMAKER":["NOOP"]},{"BACKGROUND":["ZIR:bidRangeMin_100000_bidRangeMax_125000","ZIR:bidRangeMin_75000_bidRangeMax_100000"],"MARKETMAKER":["NOOP"]},{"BACKGROUND":["ZIR:bidRangeMin_100000_bidRangeMax_125000","ZIR:bidRangeMin_50000_bidRangeMax_100000"],"MARKETMAKER":["NOOP"]},{"BACKGROUND":["ZIR:bidRangeMin_100000_bidRangeMax_125000","ZIR:bidRangeMin_1000_bidRangeMax_2000"],"MARKETMAKER":["NOOP"]},{"BACKGROUND":["ZIR:bidRangeMin_0_bidRangeMax_1000","ZIR:bidRangeMin_0_bidRangeMax_5000"],"MARKETMAKER":["NOOP"]},{"BACKGROUND":["ZIR:bidRangeMin_0_bidRangeMax_5000","ZIR:bidRangeMin_100000_bidRangeMax_125000"],"MARKETMAKER":["NOOP"]}]